[{"timestamp":1589394980948,"files":[{"filename":"bundle.*****.js","previous":6788,"size":6812,"diff":24},{"filename":"polyfills.*****.js","previous":2012,"size":2012,"diff":0},{"filename":"route-artist/index.tsx.chunk.*****.js","previous":7036,"size":7109,"diff":73},{"filename":"bundle.36c6a.css","previous":2137,"size":0,"diff":-2137},{"filename":"bundle.d5735.css","previous":0,"size":2185,"diff":2185},{"filename":"route-home/index.tsx.chunk.*****.js","previous":0,"size":1113,"diff":1113}]},{"timestamp":1589331664117,"files":[{"filename":"bundle.*****.js","previous":6788,"size":6788,"diff":0},{"filename":"polyfills.*****.js","previous":2012,"size":2012,"diff":0},{"filename":"route-artist/index.tsx.chunk.*****.js","previous":7036,"size":7036,"diff":0},{"filename":"bundle.1359a.css","previous":141097,"size":0,"diff":-141097},{"filename":"bundle.36c6a.css","previous":0,"size":2137,"diff":2137}]},{"timestamp":1589331618055,"files":[{"filename":"bundle.36c6a.css","previous":2137,"size":0,"diff":-2137},{"filename":"bundle.*****.js","previous":6788,"size":6788,"diff":0},{"filename":"polyfills.*****.js","previous":2012,"size":2012,"diff":0},{"filename":"route-artist/index.tsx.chunk.*****.js","previous":7036,"size":7036,"diff":0},{"filename":"bundle.1359a.css","previous":0,"size":141097,"diff":141097}]},{"timestamp":1589330613172,"files":[{"filename":"bundle.36c6a.css","previous":2137,"size":2137,"diff":0},{"filename":"bundle.*****.js","previous":6789,"size":6788,"diff":-1},{"filename":"polyfills.*****.js","previous":2012,"size":2012,"diff":0},{"filename":"route-artist/index.tsx.chunk.*****.js","previous":7042,"size":7036,"diff":-6}]},{"timestamp":1589326624164,"files":[{"filename":"bundle.36c6a.css","previous":0,"size":2137,"diff":2137},{"filename":"bundle.*****.js","previous":0,"size":6789,"diff":6789},{"filename":"polyfills.*****.js","previous":0,"size":2012,"diff":2012},{"filename":"route-artist/index.tsx.chunk.*****.js","previous":0,"size":7042,"diff":7042}]}]
